{
  "model_id": "SO019",
  "airline_code": "SO",
  "airline": "Sonstige Airlines",
  "airline_row": "United Parcel Service (UPS)",
  "manufacturer": "Gemini Jets",
  "aircraft_name": "",
  "livery_note": "",
  "extra_info": "\"Worldwide Services\"-Sticker",
  "shop_url": "https://www.ebay.de/itm/127949338697",
  "aircraft_id": "BOE-757-200PF",
  "aircraft_type": "Boeing 757-200PF",
  "registration": "N470UP",
  "livery_name": "",
  "parent_livery": "",
  "zusatzinfo": "I:\"Worldwide Services\"-Sticker",
  "model_extra": "",
  "special_note": "",
  "shop": "Ebay hermannjosef1461",
  "price": 12.0,
  "shipping_allocated": 3.96,
  "flown": null,
  "postcards_raw": "I:andere Kennung, anderer Sticker | U:https://jjpostcards.com/de/ansichtskarten/20955-ups-b757.html",
  "postcard_info": "andere Kennung, anderer Sticker",
  "postcard_url": "https://jjpostcards.com/de/ansichtskarten/20955-ups-b757.html",
  "postcard_price": 0.85,
  "postcards": [
    {
      "id": "PC-SO019-01",
      "label": "andere Kennung, anderer Sticker",
      "url": "https://jjpostcards.com/de/ansichtskarten/20955-ups-b757.html",
      "price": 0.85
    }
  ],
  "photo": "https://www.planespotters.net/photo/884756/n470up-united-parcel-service-ups-boeing-757-24apf",
  "photo_source_url": "https://www.planespotters.net/photo/884756/n470up-united-parcel-service-ups-boeing-757-24apf",
  "photo_image_url": "https://cdn.plnspttrs.net/08483/n470up-united-parcel-service-ups-boeing-757-24apf_PlanespottersNet_884756_2ecae46195_o.jpg",
  "photo_credit": "Hector A Rivera Valentin -HR Planespotter",
  "arrived_excel": "2026-07-16",
  "arrived": "2026-07-16",
  "ordered_at": null,
  "ordered": false,
  "wishlist": false,
  "wishlist_prio": null,
  "status": "owned",
  "source": {
    "sheet": "Sonstige",
    "row": "14"
  },
  "aircraft": {
    "aircraft_id": "BOE-757-200PF",
    "type": "Boeing 757-200PF",
    "registration": "N470UP",
    "wingtip": "NONE",
    "has_wingtip": false
  },
  "livery": {
    "code": "",
    "parent": "",
    "notes_raw": "I:\"Worldwide Services\"-Sticker",
    "note": ""
  },
  "model": {
    "scale": "1:400",
    "manufacturer": "Gemini Jets",
    "model_number": "",
    "shop": "Ebay hermannjosef1461",
    "price": 12.0,
    "shipping_allocated": 3.96,
    "arrived": "2026-07-16",
    "ordered_at": null,
    "ordered": false,
    "present": true,
    "wishlist": false,
    "wishlist_prio": null,
    "status": "owned",
    "flown": null,
    "special_note": "",
    "model_extra": ""
  },
  "links": {
    "postcards_raw": "I:andere Kennung, anderer Sticker | U:https://jjpostcards.com/de/ansichtskarten/20955-ups-b757.html",
    "postcard_url": "https://jjpostcards.com/de/ansichtskarten/20955-ups-b757.html",
    "photo": "https://www.planespotters.net/photo/884756/n470up-united-parcel-service-ups-boeing-757-24apf",
    "shop": "Ebay hermannjosef1461",
    "shop_url": "https://www.ebay.de/itm/127949338697"
  },
  "logo": {
    "id": "5X_UPS",
    "link": "https://assets.planespotters.net/files/airlines/5/united-parcel-service-ups_f6eb18_opr.png",
    "name": "-",
    "airline": "United Parcel Service (UPS)",
    "logo_speaking": "Wahr"
  },
  "aircraft_full_v8": {
    "aircraft_id": "BOE-757-200PF",
    "Typ_anzeige": "Boeing 757-200PF",
    "Hersteller": "Boeing",
    "Baureihe": "757",
    "Unterserie": "-200PF",
    "Marketingname": "Package Freighter",
    "Alternate_designations": "Boeing 757-23APF|757-200PF|757-200 Package Freighter",
    "parent_aircraft_id": "BOE-757-200",
    "ICAO": "B752",
    "IATA": "75F",
    "Wingtip": "NONE",
    "Rumpf": "SingleAisle",
    "MarketSegment": "MediumHaul",
    "Role": "CARGO",
    "Flugzeugtyp": "Landflugzeug",
    "Erstflug": "1987",
    "Status": "aktiv",
    "Antrieb": "Jet",
    "Triebwerke": "2",
    "Reichweite": "Mittel",
    "Passengers": "0",
    "Length": "47,32",
    "Wingspan": "38,05",
    "Height": "13,56",
    "Wiki": "https://de.wikipedia.org/wiki/Boeing_757"
  }
}