{
  "model_id": "WIS-SK-34",
  "airline_code": "SK",
  "airline": "SAS",
  "airline_row": "SAS",
  "manufacturer": "Witty Wings",
  "aircraft_name": "Ring Viking",
  "livery_note": "",
  "extra_info": "",
  "shop_url": "https://www.ebay.de/itm/297706519154?_skw=1%2F400&itmmeta=01K8TKQVTF0TY9F03N800XEPWF&hash=item4550b0fa72%3Ag%3AhvQAAeSw9K5o-mRx&LH_Auction=1",
  "aircraft_id": "CON-CV990",
  "aircraft_type": "Convair CV-990 Coronado",
  "registration": "SE-DAZ",
  "livery_name": "",
  "parent_livery": "",
  "zusatzinfo": "N:Ring Viking",
  "model_extra": "",
  "special_note": "",
  "shop": "Ebay Felindre Diecast",
  "price": null,
  "shipping_allocated": null,
  "flown": null,
  "postcards_raw": "I:andere Kennung | U:https://jjpostcards.com/de/ansichtskarten/29567-sas-cv-990.html",
  "postcard_info": "andere Kennung",
  "postcard_url": "https://jjpostcards.com/de/ansichtskarten/29567-sas-cv-990.html",
  "postcard_price": 1.35,
  "postcards": [
    {
      "id": "PC-WIS-SK-34-01",
      "label": "andere Kennung",
      "url": "https://jjpostcards.com/de/ansichtskarten/29567-sas-cv-990.html",
      "price": 1.35
    }
  ],
  "photo": "https://www.airhistory.net/photo/114742/SE-DAZ",
  "photo_source_url": "https://www.airhistory.net/photo/114742/SE-DAZ",
  "photo_image_url": "",
  "photo_credit": "",
  "arrived_excel": "",
  "arrived": null,
  "ordered_at": null,
  "ordered": false,
  "wishlist": true,
  "wishlist_prio": 2,
  "status": "wishlist",
  "source": {
    "sheet": "SAS",
    "row": "34"
  },
  "aircraft": {
    "aircraft_id": "CON-CV990",
    "type": "Convair CV-990 Coronado",
    "registration": "SE-DAZ",
    "wingtip": "NONE",
    "has_wingtip": false
  },
  "livery": {
    "code": "",
    "parent": "",
    "notes_raw": "N:Ring Viking",
    "note": ""
  },
  "model": {
    "scale": "1:400",
    "manufacturer": "Witty Wings",
    "model_number": "",
    "shop": "Ebay Felindre Diecast",
    "price": null,
    "shipping_allocated": null,
    "arrived": null,
    "ordered_at": null,
    "ordered": false,
    "present": false,
    "wishlist": true,
    "wishlist_prio": 2,
    "status": "wishlist",
    "flown": null,
    "special_note": "",
    "model_extra": ""
  },
  "links": {
    "postcards_raw": "I:andere Kennung | U:https://jjpostcards.com/de/ansichtskarten/29567-sas-cv-990.html",
    "postcard_url": "https://jjpostcards.com/de/ansichtskarten/29567-sas-cv-990.html",
    "photo": "https://www.airhistory.net/photo/114742/SE-DAZ",
    "shop": "Ebay Felindre Diecast",
    "shop_url": "https://www.ebay.de/itm/297706519154?_skw=1%2F400&itmmeta=01K8TKQVTF0TY9F03N800XEPWF&hash=item4550b0fa72%3Ag%3AhvQAAeSw9K5o-mRx&LH_Auction=1"
  },
  "logo": {
    "id": "SK_SAS",
    "link": "https://assets.planespotters.net/files/airlines/2/sas_160938_opk.jpg",
    "name": "Scandinavian Airlines System Denmark-Norway-Sweden",
    "airline": "SAS",
    "logo_speaking": "Wahr"
  },
  "aircraft_full_v8": {
    "aircraft_id": "CON-CV990",
    "Typ_anzeige": "Convair CV-990 Coronado",
    "Hersteller": "Convair",
    "Baureihe": "CV-990",
    "Unterserie": "",
    "Marketingname": "CV-990 Coronado",
    "Alternate_designations": "Convair CV-990|Coronado",
    "parent_aircraft_id": "",
    "ICAO": "CV99",
    "IATA": "990",
    "Wingtip": "NONE",
    "Rumpf": "SingleAisle",
    "MarketSegment": "Standard",
    "Role": "PAX",
    "Flugzeugtyp": "Landflugzeug",
    "Erstflug": "1961",
    "Status": "ausgemustert",
    "Antrieb": "Jet",
    "Triebwerke": "4",
    "Reichweite": "Lang",
    "Passengers": "96",
    "Length": "42,36",
    "Wingspan": "36,58",
    "Height": "11,68",
    "Wiki": "https://de.wikipedia.org/wiki/Convair_CV-990"
  }
}