{
  "model_id": "SK002",
  "airline_code": "SK",
  "airline": "SAS",
  "airline_row": "SAS",
  "manufacturer": "JC Wings",
  "aircraft_name": "Vermund Viking",
  "livery_note": "",
  "extra_info": "",
  "shop_url": "https://www.aviation-center-berlin.de/p/JC40249",
  "aircraft_id": "AIB-A320-200",
  "aircraft_type": "Airbus A320-200",
  "registration": "OY-KAR",
  "livery_name": "",
  "parent_livery": "",
  "zusatzinfo": "N:Vermund Viking",
  "special_note": "",
  "shop": "Aviation Center Berlin",
  "price": 47.34,
  "shipping_allocated": 14.06,
  "flown": true,
  "postcard": "andere Kennung; https://jjpostcards.com/de/ansichtskarten/27072-sas-a320.html",
  "postcard_price": 0.85,
  "photo": "https://www.planespotters.net/photo/869467/oy-kar-sas-scandinavian-airlines-airbus-a320-232",
  "arrived_excel": "2025-07-22",
  "arrived": "2025-07-22",
  "source": {
    "sheet": "SAS",
    "row": "7"
  },
  "aircraft": {
    "aircraft_id": "AIB-A320-200",
    "type": "Airbus A320-200",
    "registration": "OY-KAR"
  },
  "livery": {
    "code": "",
    "parent": "",
    "notes_raw": "N:Vermund Viking",
    "note": ""
  },
  "model": {
    "scale": "1:400",
    "manufacturer": "JC Wings",
    "model_number": "",
    "shop": "Aviation Center Berlin",
    "price": 47.34,
    "shipping_allocated": 14.06,
    "arrived": "2025-07-22",
    "flown": true,
    "special_note": ""
  },
  "links": {
    "postcard": "andere Kennung; https://jjpostcards.com/de/ansichtskarten/27072-sas-a320.html",
    "photo": "https://www.planespotters.net/photo/869467/oy-kar-sas-scandinavian-airlines-airbus-a320-232",
    "shop": "Aviation Center Berlin",
    "shop_url": "https://www.aviation-center-berlin.de/p/JC40249"
  },
  "logo": {
    "id": "SK_SAS",
    "link": "https://assets.planespotters.net/files/airlines/2/sas_160938_opk.jpg",
    "name": "Scandinavian Airlines System Denmark-Norway-Sweden",
    "airline": "SAS"
  },
  "aircraft_full_v8": {
    "aircraft_id": "AIB-A320-200",
    "Typ_anzeige": "Airbus A320-200",
    "Hersteller": "Airbus",
    "Baureihe": "A320",
    "Unterserie": "-200",
    "Marketingname": "",
    "Alternate_designations": "",
    "parent_aircraft_id": "",
    "ICAO": "A320",
    "IATA": "320",
    "Wingtip": "NONE",
    "Rumpf": "SingleAisle",
    "MarketSegment": "Standard",
    "Role": "PAX",
    "Flugzeugtyp": "Landflugzeug",
    "Erstflug": "1988",
    "Status": "aktiv",
    "Antrieb": "Jet",
    "Triebwerke": "2",
    "Reichweite": "Mittel",
    "Passengers": "180",
    "Length": "37,57",
    "Wingspan": "34,1",
    "Height": "11,76",
    "Wiki": "https://de.wikipedia.org/wiki/Airbus_A320#A320-200"
  }
}